{
  "_format": "hh-sol-cache-2",
  "files": {
    "/Users/andie/Documents/Work/erc6551/contracts/ERC6551Account.sol": {
      "lastModificationDate": 1726828270737,
      "contentHash": "e252d38a72704f449d37087bb8ae8ddc",
      "sourceName": "contracts/ERC6551Account.sol",
      "solcConfig": {
        "version": "0.8.20",
        "settings": {
          "evmVersion": "paris",
          "optimizer": {
            "enabled": false,
            "runs": 200
          },
          "outputSelection": {
            "*": {
              "*": [
                "abi",
                "evm.bytecode",
                "evm.deployedBytecode",
                "evm.methodIdentifiers",
                "metadata"
              ],
              "": [
                "ast"
              ]
            }
          }
        }
      },
      "imports": [
        "@openzeppelin/contracts/utils/introspection/IERC165.sol",
        "@openzeppelin/contracts/token/ERC721/IERC721.sol",
        "@openzeppelin/contracts/interfaces/IERC1271.sol",
        "@openzeppelin/contracts/utils/cryptography/SignatureChecker.sol",
        "../interfaces/IERC6551Account.sol",
        "../interfaces/IERC6551Executable.sol"
      ],
      "versionPragmas": [
        "^0.8.9"
      ],
      "artifacts": [
        "ERC6551Account"
      ]
    },
    "/Users/andie/Documents/Work/erc6551/interfaces/IERC6551Account.sol": {
      "lastModificationDate": 1726828019007,
      "contentHash": "0cacc7f1e06152315ba66cefbb99b12e",
      "sourceName": "interfaces/IERC6551Account.sol",
      "solcConfig": {
        "version": "0.8.20",
        "settings": {
          "evmVersion": "paris",
          "optimizer": {
            "enabled": false,
            "runs": 200
          },
          "outputSelection": {
            "*": {
              "*": [
                "abi",
                "evm.bytecode",
                "evm.deployedBytecode",
                "evm.methodIdentifiers",
                "metadata"
              ],
              "": [
                "ast"
              ]
            }
          }
        }
      },
      "imports": [],
      "versionPragmas": [
        "^0.8.9"
      ],
      "artifacts": [
        "IERC6551Account"
      ]
    },
    "/Users/andie/Documents/Work/erc6551/interfaces/IERC6551Executable.sol": {
      "lastModificationDate": 1726828022929,
      "contentHash": "26003dc7f41bfab587dfbac5bb00b083",
      "sourceName": "interfaces/IERC6551Executable.sol",
      "solcConfig": {
        "version": "0.8.20",
        "settings": {
          "evmVersion": "paris",
          "optimizer": {
            "enabled": false,
            "runs": 200
          },
          "outputSelection": {
            "*": {
              "*": [
                "abi",
                "evm.bytecode",
                "evm.deployedBytecode",
                "evm.methodIdentifiers",
                "metadata"
              ],
              "": [
                "ast"
              ]
            }
          }
        }
      },
      "imports": [],
      "versionPragmas": [
        "^0.8.9"
      ],
      "artifacts": [
        "IERC6551Executable"
      ]
    },
    "/Users/andie/Documents/Work/erc6551/node_modules/@openzeppelin/contracts/utils/introspection/IERC165.sol": {
      "lastModificationDate": 1726805800515,
      "contentHash": "de0163561b417b800d01749cbbe2147e",
      "sourceName": "@openzeppelin/contracts/utils/introspection/IERC165.sol",
      "solcConfig": {
        "version": "0.8.20",
        "settings": {
          "evmVersion": "paris",
          "optimizer": {
            "enabled": false,
            "runs": 200
          },
          "outputSelection": {
            "*": {
              "*": [
                "abi",
                "evm.bytecode",
                "evm.deployedBytecode",
                "evm.methodIdentifiers",
                "metadata"
              ],
              "": [
                "ast"
              ]
            }
          }
        }
      },
      "imports": [],
      "versionPragmas": [
        "^0.8.20"
      ],
      "artifacts": [
        "IERC165"
      ]
    },
    "/Users/andie/Documents/Work/erc6551/node_modules/@openzeppelin/contracts/interfaces/IERC1271.sol": {
      "lastModificationDate": 1726805800515,
      "contentHash": "12a8c0358597a0dc191410b1259e61ee",
      "sourceName": "@openzeppelin/contracts/interfaces/IERC1271.sol",
      "solcConfig": {
        "version": "0.8.20",
        "settings": {
          "evmVersion": "paris",
          "optimizer": {
            "enabled": false,
            "runs": 200
          },
          "outputSelection": {
            "*": {
              "*": [
                "abi",
                "evm.bytecode",
                "evm.deployedBytecode",
                "evm.methodIdentifiers",
                "metadata"
              ],
              "": [
                "ast"
              ]
            }
          }
        }
      },
      "imports": [],
      "versionPragmas": [
        "^0.8.20"
      ],
      "artifacts": [
        "IERC1271"
      ]
    },
    "/Users/andie/Documents/Work/erc6551/node_modules/@openzeppelin/contracts/utils/cryptography/SignatureChecker.sol": {
      "lastModificationDate": 1726805800520,
      "contentHash": "67e1b232791e1ea1cf6475bd4aaed191",
      "sourceName": "@openzeppelin/contracts/utils/cryptography/SignatureChecker.sol",
      "solcConfig": {
        "version": "0.8.20",
        "settings": {
          "evmVersion": "paris",
          "optimizer": {
            "enabled": false,
            "runs": 200
          },
          "outputSelection": {
            "*": {
              "*": [
                "abi",
                "evm.bytecode",
                "evm.deployedBytecode",
                "evm.methodIdentifiers",
                "metadata"
              ],
              "": [
                "ast"
              ]
            }
          }
        }
      },
      "imports": [
        "./ECDSA.sol",
        "../../interfaces/IERC1271.sol"
      ],
      "versionPragmas": [
        "^0.8.20"
      ],
      "artifacts": [
        "SignatureChecker"
      ]
    },
    "/Users/andie/Documents/Work/erc6551/node_modules/@openzeppelin/contracts/token/ERC721/IERC721.sol": {
      "lastModificationDate": 1726805800518,
      "contentHash": "5df8fdb527e563085847cad29e3c5f2e",
      "sourceName": "@openzeppelin/contracts/token/ERC721/IERC721.sol",
      "solcConfig": {
        "version": "0.8.20",
        "settings": {
          "evmVersion": "paris",
          "optimizer": {
            "enabled": false,
            "runs": 200
          },
          "outputSelection": {
            "*": {
              "*": [
                "abi",
                "evm.bytecode",
                "evm.deployedBytecode",
                "evm.methodIdentifiers",
                "metadata"
              ],
              "": [
                "ast"
              ]
            }
          }
        }
      },
      "imports": [
        "../../utils/introspection/IERC165.sol"
      ],
      "versionPragmas": [
        "^0.8.20"
      ],
      "artifacts": [
        "IERC721"
      ]
    },
    "/Users/andie/Documents/Work/erc6551/node_modules/@openzeppelin/contracts/utils/cryptography/ECDSA.sol": {
      "lastModificationDate": 1726805800507,
      "contentHash": "b96e0d7a3c2b185342c7d083d765b61f",
      "sourceName": "@openzeppelin/contracts/utils/cryptography/ECDSA.sol",
      "solcConfig": {
        "version": "0.8.20",
        "settings": {
          "evmVersion": "paris",
          "optimizer": {
            "enabled": false,
            "runs": 200
          },
          "outputSelection": {
            "*": {
              "*": [
                "abi",
                "evm.bytecode",
                "evm.deployedBytecode",
                "evm.methodIdentifiers",
                "metadata"
              ],
              "": [
                "ast"
              ]
            }
          }
        }
      },
      "imports": [],
      "versionPragmas": [
        "^0.8.20"
      ],
      "artifacts": [
        "ECDSA"
      ]
    },
    "/Users/andie/Documents/Work/erc6551/node_modules/@openzeppelin/contracts/interfaces/IERC721.sol": {
      "lastModificationDate": 1726805800518,
      "contentHash": "d8d23fc2f55ed934d1a1b91c9afd8526",
      "sourceName": "@openzeppelin/contracts/interfaces/IERC721.sol",
      "solcConfig": {
        "version": "0.8.20",
        "settings": {
          "evmVersion": "paris",
          "optimizer": {
            "enabled": false,
            "runs": 200
          },
          "outputSelection": {
            "*": {
              "*": [
                "abi",
                "evm.bytecode",
                "evm.deployedBytecode",
                "evm.methodIdentifiers",
                "metadata"
              ],
              "": [
                "ast"
              ]
            }
          }
        }
      },
      "imports": [
        "../token/ERC721/IERC721.sol"
      ],
      "versionPragmas": [
        "^0.8.20"
      ],
      "artifacts": []
    },
    "/Users/andie/Documents/Work/erc6551/node_modules/@openzeppelin/contracts/interfaces/IERC4906.sol": {
      "lastModificationDate": 1726805800517,
      "contentHash": "7f130e0d70179d683e9b9df0dda38a51",
      "sourceName": "@openzeppelin/contracts/interfaces/IERC4906.sol",
      "solcConfig": {
        "version": "0.8.20",
        "settings": {
          "evmVersion": "paris",
          "optimizer": {
            "enabled": false,
            "runs": 200
          },
          "outputSelection": {
            "*": {
              "*": [
                "abi",
                "evm.bytecode",
                "evm.deployedBytecode",
                "evm.methodIdentifiers",
                "metadata"
              ],
              "": [
                "ast"
              ]
            }
          }
        }
      },
      "imports": [
        "./IERC165.sol",
        "./IERC721.sol"
      ],
      "versionPragmas": [
        "^0.8.20"
      ],
      "artifacts": [
        "IERC4906"
      ]
    },
    "/Users/andie/Documents/Work/erc6551/node_modules/@openzeppelin/contracts/interfaces/IERC165.sol": {
      "lastModificationDate": 1726805800515,
      "contentHash": "f808b485ee0cdc6768ee8385ae5f9a2a",
      "sourceName": "@openzeppelin/contracts/interfaces/IERC165.sol",
      "solcConfig": {
        "version": "0.8.20",
        "settings": {
          "evmVersion": "paris",
          "optimizer": {
            "enabled": false,
            "runs": 200
          },
          "outputSelection": {
            "*": {
              "*": [
                "abi",
                "evm.bytecode",
                "evm.deployedBytecode",
                "evm.methodIdentifiers",
                "metadata"
              ],
              "": [
                "ast"
              ]
            }
          }
        }
      },
      "imports": [
        "../utils/introspection/IERC165.sol"
      ],
      "versionPragmas": [
        "^0.8.20"
      ],
      "artifacts": []
    },
    "/Users/andie/Documents/Work/erc6551/node_modules/@openzeppelin/contracts/utils/introspection/ERC165.sol": {
      "lastModificationDate": 1726805800508,
      "contentHash": "6a55c353946e471d9792965d06208295",
      "sourceName": "@openzeppelin/contracts/utils/introspection/ERC165.sol",
      "solcConfig": {
        "version": "0.8.20",
        "settings": {
          "evmVersion": "paris",
          "optimizer": {
            "enabled": false,
            "runs": 200
          },
          "outputSelection": {
            "*": {
              "*": [
                "abi",
                "evm.bytecode",
                "evm.deployedBytecode",
                "evm.methodIdentifiers",
                "metadata"
              ],
              "": [
                "ast"
              ]
            }
          }
        }
      },
      "imports": [
        "./IERC165.sol"
      ],
      "versionPragmas": [
        "^0.8.20"
      ],
      "artifacts": [
        "ERC165"
      ]
    },
    "/Users/andie/Documents/Work/erc6551/node_modules/@openzeppelin/contracts/token/ERC721/ERC721.sol": {
      "lastModificationDate": 1726805800511,
      "contentHash": "1e64e2ad597dc5b2dae11346502baad4",
      "sourceName": "@openzeppelin/contracts/token/ERC721/ERC721.sol",
      "solcConfig": {
        "version": "0.8.20",
        "settings": {
          "evmVersion": "paris",
          "optimizer": {
            "enabled": false,
            "runs": 200
          },
          "outputSelection": {
            "*": {
              "*": [
                "abi",
                "evm.bytecode",
                "evm.deployedBytecode",
                "evm.methodIdentifiers",
                "metadata"
              ],
              "": [
                "ast"
              ]
            }
          }
        }
      },
      "imports": [
        "./IERC721.sol",
        "./IERC721Receiver.sol",
        "./extensions/IERC721Metadata.sol",
        "../../utils/Context.sol",
        "../../utils/Strings.sol",
        "../../utils/introspection/ERC165.sol",
        "../../interfaces/draft-IERC6093.sol"
      ],
      "versionPragmas": [
        "^0.8.20"
      ],
      "artifacts": [
        "ERC721"
      ]
    },
    "/Users/andie/Documents/Work/erc6551/node_modules/@openzeppelin/contracts/utils/Context.sol": {
      "lastModificationDate": 1726805800506,
      "contentHash": "67bfbc07588eb8683b3fd8f6f909563e",
      "sourceName": "@openzeppelin/contracts/utils/Context.sol",
      "solcConfig": {
        "version": "0.8.20",
        "settings": {
          "evmVersion": "paris",
          "optimizer": {
            "enabled": false,
            "runs": 200
          },
          "outputSelection": {
            "*": {
              "*": [
                "abi",
                "evm.bytecode",
                "evm.deployedBytecode",
                "evm.methodIdentifiers",
                "metadata"
              ],
              "": [
                "ast"
              ]
            }
          }
        }
      },
      "imports": [],
      "versionPragmas": [
        "^0.8.20"
      ],
      "artifacts": [
        "Context"
      ]
    },
    "/Users/andie/Documents/Work/erc6551/node_modules/@openzeppelin/contracts/interfaces/draft-IERC6093.sol": {
      "lastModificationDate": 1726805800506,
      "contentHash": "4aefc698f77ecbace7f401257dfe182d",
      "sourceName": "@openzeppelin/contracts/interfaces/draft-IERC6093.sol",
      "solcConfig": {
        "version": "0.8.20",
        "settings": {
          "evmVersion": "paris",
          "optimizer": {
            "enabled": false,
            "runs": 200
          },
          "outputSelection": {
            "*": {
              "*": [
                "abi",
                "evm.bytecode",
                "evm.deployedBytecode",
                "evm.methodIdentifiers",
                "metadata"
              ],
              "": [
                "ast"
              ]
            }
          }
        }
      },
      "imports": [],
      "versionPragmas": [
        "^0.8.20"
      ],
      "artifacts": [
        "IERC1155Errors",
        "IERC20Errors",
        "IERC721Errors"
      ]
    },
    "/Users/andie/Documents/Work/erc6551/node_modules/@openzeppelin/contracts/utils/Strings.sol": {
      "lastModificationDate": 1726805800521,
      "contentHash": "ba57ff4ddf1d9cae9d2009792795b7f6",
      "sourceName": "@openzeppelin/contracts/utils/Strings.sol",
      "solcConfig": {
        "version": "0.8.20",
        "settings": {
          "evmVersion": "paris",
          "optimizer": {
            "enabled": false,
            "runs": 200
          },
          "outputSelection": {
            "*": {
              "*": [
                "abi",
                "evm.bytecode",
                "evm.deployedBytecode",
                "evm.methodIdentifiers",
                "metadata"
              ],
              "": [
                "ast"
              ]
            }
          }
        }
      },
      "imports": [
        "./math/Math.sol",
        "./math/SignedMath.sol"
      ],
      "versionPragmas": [
        "^0.8.20"
      ],
      "artifacts": [
        "Strings"
      ]
    },
    "/Users/andie/Documents/Work/erc6551/node_modules/@openzeppelin/contracts/token/ERC721/IERC721Receiver.sol": {
      "lastModificationDate": 1726805800518,
      "contentHash": "fc8a9841f4bdd6329c26a00d5e75f4b3",
      "sourceName": "@openzeppelin/contracts/token/ERC721/IERC721Receiver.sol",
      "solcConfig": {
        "version": "0.8.20",
        "settings": {
          "evmVersion": "paris",
          "optimizer": {
            "enabled": false,
            "runs": 200
          },
          "outputSelection": {
            "*": {
              "*": [
                "abi",
                "evm.bytecode",
                "evm.deployedBytecode",
                "evm.methodIdentifiers",
                "metadata"
              ],
              "": [
                "ast"
              ]
            }
          }
        }
      },
      "imports": [],
      "versionPragmas": [
        "^0.8.20"
      ],
      "artifacts": [
        "IERC721Receiver"
      ]
    },
    "/Users/andie/Documents/Work/erc6551/node_modules/@openzeppelin/contracts/token/ERC721/extensions/IERC721Metadata.sol": {
      "lastModificationDate": 1726805800518,
      "contentHash": "12c206f185cb951213799561fdcaa40d",
      "sourceName": "@openzeppelin/contracts/token/ERC721/extensions/IERC721Metadata.sol",
      "solcConfig": {
        "version": "0.8.20",
        "settings": {
          "evmVersion": "paris",
          "optimizer": {
            "enabled": false,
            "runs": 200
          },
          "outputSelection": {
            "*": {
              "*": [
                "abi",
                "evm.bytecode",
                "evm.deployedBytecode",
                "evm.methodIdentifiers",
                "metadata"
              ],
              "": [
                "ast"
              ]
            }
          }
        }
      },
      "imports": [
        "../IERC721.sol"
      ],
      "versionPragmas": [
        "^0.8.20"
      ],
      "artifacts": [
        "IERC721Metadata"
      ]
    },
    "/Users/andie/Documents/Work/erc6551/node_modules/@openzeppelin/contracts/utils/math/Math.sol": {
      "lastModificationDate": 1726805800519,
      "contentHash": "718fa8ba0ff269c92e364c1429d9de57",
      "sourceName": "@openzeppelin/contracts/utils/math/Math.sol",
      "solcConfig": {
        "version": "0.8.20",
        "settings": {
          "evmVersion": "paris",
          "optimizer": {
            "enabled": false,
            "runs": 200
          },
          "outputSelection": {
            "*": {
              "*": [
                "abi",
                "evm.bytecode",
                "evm.deployedBytecode",
                "evm.methodIdentifiers",
                "metadata"
              ],
              "": [
                "ast"
              ]
            }
          }
        }
      },
      "imports": [],
      "versionPragmas": [
        "^0.8.20"
      ],
      "artifacts": [
        "Math"
      ]
    },
    "/Users/andie/Documents/Work/erc6551/node_modules/@openzeppelin/contracts/utils/math/SignedMath.sol": {
      "lastModificationDate": 1726805800521,
      "contentHash": "b6c6bdc7aaca4fe5b680760a72e09d3e",
      "sourceName": "@openzeppelin/contracts/utils/math/SignedMath.sol",
      "solcConfig": {
        "version": "0.8.20",
        "settings": {
          "evmVersion": "paris",
          "optimizer": {
            "enabled": false,
            "runs": 200
          },
          "outputSelection": {
            "*": {
              "*": [
                "abi",
                "evm.bytecode",
                "evm.deployedBytecode",
                "evm.methodIdentifiers",
                "metadata"
              ],
              "": [
                "ast"
              ]
            }
          }
        }
      },
      "imports": [],
      "versionPragmas": [
        "^0.8.20"
      ],
      "artifacts": [
        "SignedMath"
      ]
    },
    "/Users/andie/Documents/Work/erc6551/node_modules/@openzeppelin/contracts/token/ERC721/extensions/ERC721URIStorage.sol": {
      "lastModificationDate": 1726805800512,
      "contentHash": "50d770b698931f015309e77a750f54f6",
      "sourceName": "@openzeppelin/contracts/token/ERC721/extensions/ERC721URIStorage.sol",
      "solcConfig": {
        "version": "0.8.20",
        "settings": {
          "evmVersion": "paris",
          "optimizer": {
            "enabled": false,
            "runs": 200
          },
          "outputSelection": {
            "*": {
              "*": [
                "abi",
                "evm.bytecode",
                "evm.deployedBytecode",
                "evm.methodIdentifiers",
                "metadata"
              ],
              "": [
                "ast"
              ]
            }
          }
        }
      },
      "imports": [
        "../ERC721.sol",
        "../../../utils/Strings.sol",
        "../../../interfaces/IERC4906.sol",
        "../../../interfaces/IERC165.sol"
      ],
      "versionPragmas": [
        "^0.8.20"
      ],
      "artifacts": [
        "ERC721URIStorage"
      ]
    },
    "/Users/andie/Documents/Work/erc6551/contracts/Pinnie.sol": {
      "lastModificationDate": 1726827291263,
      "contentHash": "216695d54660e5280d55da19258aba4a",
      "sourceName": "contracts/Pinnie.sol",
      "solcConfig": {
        "version": "0.8.20",
        "settings": {
          "evmVersion": "paris",
          "optimizer": {
            "enabled": false,
            "runs": 200
          },
          "outputSelection": {
            "*": {
              "*": [
                "abi",
                "evm.bytecode",
                "evm.deployedBytecode",
                "evm.methodIdentifiers",
                "metadata"
              ],
              "": [
                "ast"
              ]
            }
          }
        }
      },
      "imports": [
        "@openzeppelin/contracts/token/ERC721/ERC721.sol",
        "@openzeppelin/contracts/token/ERC721/extensions/ERC721URIStorage.sol",
        "@openzeppelin/contracts/access/Ownable.sol"
      ],
      "versionPragmas": [
        "^0.8.20"
      ],
      "artifacts": [
        "Pinnie"
      ]
    },
    "/Users/andie/Documents/Work/erc6551/node_modules/@openzeppelin/contracts/access/Ownable.sol": {
      "lastModificationDate": 1726805800519,
      "contentHash": "d3c790edc9ccf808a17c5a6cd13614fd",
      "sourceName": "@openzeppelin/contracts/access/Ownable.sol",
      "solcConfig": {
        "version": "0.8.20",
        "settings": {
          "evmVersion": "paris",
          "optimizer": {
            "enabled": false,
            "runs": 200
          },
          "outputSelection": {
            "*": {
              "*": [
                "abi",
                "evm.bytecode",
                "evm.deployedBytecode",
                "evm.methodIdentifiers",
                "metadata"
              ],
              "": [
                "ast"
              ]
            }
          }
        }
      },
      "imports": [
        "../utils/Context.sol"
      ],
      "versionPragmas": [
        "^0.8.20"
      ],
      "artifacts": [
        "Ownable"
      ]
    },
    "/Users/andie/Documents/Work/erc6551/contracts/ERC6551Registry.sol": {
      "lastModificationDate": 1726827507027,
      "contentHash": "eaed837a5a3ed9fa6ce3ce4f9bbbdae7",
      "sourceName": "contracts/ERC6551Registry.sol",
      "solcConfig": {
        "version": "0.8.20",
        "settings": {
          "evmVersion": "paris",
          "optimizer": {
            "enabled": false,
            "runs": 200
          },
          "outputSelection": {
            "*": {
              "*": [
                "abi",
                "evm.bytecode",
                "evm.deployedBytecode",
                "evm.methodIdentifiers",
                "metadata"
              ],
              "": [
                "ast"
              ]
            }
          }
        }
      },
      "imports": [
        "@openzeppelin/contracts/utils/Create2.sol",
        "../interfaces/IERC6551Registry.sol"
      ],
      "versionPragmas": [
        "^0.8.9"
      ],
      "artifacts": [
        "ERC6551BytecodeLib",
        "ERC6551Registry"
      ]
    },
    "/Users/andie/Documents/Work/erc6551/interfaces/IERC6551Registry.sol": {
      "lastModificationDate": 1726827439989,
      "contentHash": "632e3042dd769e08383f74b9836f24f7",
      "sourceName": "interfaces/IERC6551Registry.sol",
      "solcConfig": {
        "version": "0.8.20",
        "settings": {
          "evmVersion": "paris",
          "optimizer": {
            "enabled": false,
            "runs": 200
          },
          "outputSelection": {
            "*": {
              "*": [
                "abi",
                "evm.bytecode",
                "evm.deployedBytecode",
                "evm.methodIdentifiers",
                "metadata"
              ],
              "": [
                "ast"
              ]
            }
          }
        }
      },
      "imports": [],
      "versionPragmas": [
        "^0.8.9"
      ],
      "artifacts": [
        "IERC6551Registry"
      ]
    },
    "/Users/andie/Documents/Work/erc6551/node_modules/@openzeppelin/contracts/utils/Create2.sol": {
      "lastModificationDate": 1726805800506,
      "contentHash": "30964d662b27a7894b1cf10058dc8d6b",
      "sourceName": "@openzeppelin/contracts/utils/Create2.sol",
      "solcConfig": {
        "version": "0.8.20",
        "settings": {
          "evmVersion": "paris",
          "optimizer": {
            "enabled": false,
            "runs": 200
          },
          "outputSelection": {
            "*": {
              "*": [
                "abi",
                "evm.bytecode",
                "evm.deployedBytecode",
                "evm.methodIdentifiers",
                "metadata"
              ],
              "": [
                "ast"
              ]
            }
          }
        }
      },
      "imports": [],
      "versionPragmas": [
        "^0.8.20"
      ],
      "artifacts": [
        "Create2"
      ]
    }
  }
}
